README.md
pybts/__init__.py
pybts/board/__init__.py
pybts/board/board.py
pybts/board/server.py
pybts/builder.py
pybts/composites/__init__.py
pybts/composites/composite.py
pybts/composites/condition_branch.py
pybts/composites/parallel.py
pybts/composites/ppa.py
pybts/composites/selector.py
pybts/composites/sequence.py
pybts/composites/switcher.py
pybts/composites/template.py
pybts/constants.py
pybts/converter.py
pybts/decorators/__init__.py
pybts/decorators/nodes.py
pybts/display.py
pybts/main.py
pybts/nodes.py
pybts/rl/__init__.py
pybts/rl/base_class.py
pybts/rl/builder.py
pybts/rl/common.py
pybts/rl/logger.py
pybts/rl/nodes.py
pybts/rl/off_policy.py
pybts/rl/on_policy.py
pybts/rl/tree.py
pybts/templates/favicon.ico
pybts/templates/index.html
pybts/templates/static/index-BlldS3Jx.js
pybts/templates/static/index-DN1S--qx.css
pybts/templates/static/info-lb9hZOuB.png
pybts/tree.py
pybts/utility.py
pybts-1.9.0.dist-info/METADATA
pybts-1.9.0.dist-info/WHEEL
pybts-1.9.0.dist-info/entry_points.txt
pybts-1.9.0.dist-info/RECORD
