Metadata-Version: 2.1
Name: pybts
Version: 1.9.0
Summary: 
Home-page: https://github.com/wangtong2015/pybts
Keywords: BehaviorTree,AI
Author: 王童
Author-email: 785271992@qq.com
Requires-Python: >=3.9,<4.0
Classifier: Programming Language :: Python :: 3
Classifier: Programming Language :: Python :: 3.9
Classifier: Programming Language :: Python :: 3.10
Classifier: Programming Language :: Python :: 3.11
Classifier: Programming Language :: Python :: 3.12
Provides-Extra: rl
Requires-Dist: flask (>=3.0.2,<4.0.0)
Requires-Dist: gymnasium (>=0.29.1,<0.30.0) ; extra == "rl"
Requires-Dist: jinja2 (>=3.1.3,<4.0.0)
Requires-Dist: py-trees (>=2.2.3,<3.0.0)
Requires-Dist: stable-baselines3 (>=2.3.0,<3.0.0) ; extra == "rl"
Requires-Dist: torch (>=2.2.2,<3.0.0) ; extra == "rl"
Requires-Dist: tqdm (>=4.66.2,<5.0.0)
Project-URL: Repository, https://github.com/wangtong2015/pybts
